taskfarm/__init__.py
taskfarm/__version__.py
taskfarm/app.py
taskfarm/application.py
taskfarm/config.py
taskfarm/manage.py
taskfarm/models.py
taskfarm/routes.py
taskfarm-0.4.0.dist-info/LICENSE
taskfarm-0.4.0.dist-info/METADATA
taskfarm-0.4.0.dist-info/WHEEL
taskfarm-0.4.0.dist-info/entry_points.txt
taskfarm-0.4.0.dist-info/top_level.txt
taskfarm-0.4.0.dist-info/zip-safe
taskfarm-0.4.0.dist-info/RECORD
